ibm_metrics_plugin_artifacts/__init__.py
ibm_metrics_plugin_artifacts/artifacts/__init__.py
ibm_metrics_plugin_artifacts/artifacts/datasets/prompt_leakage_data.csv
ibm_metrics_plugin_artifacts/artifacts/datasets/risk_eval_data.json
ibm_metrics_plugin_artifacts/artifacts/datasets/adversarial_robustness/__init__.py
ibm_metrics_plugin_artifacts/artifacts/datasets/adversarial_robustness/risk_eval_data_de.json
ibm_metrics_plugin_artifacts/artifacts/datasets/adversarial_robustness/risk_eval_data_fr.json
ibm_metrics_plugin_artifacts/artifacts/datasets/adversarial_robustness/risk_eval_data_ja.json
ibm_metrics_plugin_artifacts/artifacts/datasets/system_prompt_leakage/__init__.py
ibm_metrics_plugin_artifacts/artifacts/datasets/system_prompt_leakage/prompt_leakage_data_de.csv
ibm_metrics_plugin_artifacts/artifacts/datasets/system_prompt_leakage/prompt_leakage_data_fr.csv
ibm_metrics_plugin_artifacts/artifacts/datasets/system_prompt_leakage/prompt_leakage_data_ja.csv
ibm_metrics_plugin_artifacts/artifacts/models/__init__.py
ibm_metrics_plugin_artifacts/artifacts/models/sentence-transformers/__init__.py
ibm_metrics_plugin_artifacts/core/__init__.py
ibm_metrics_plugin_artifacts/core/load_artifacts.py
ibm_metrics_plugin_artifacts/core/model_downloader.py
ibm_metrics_plugin_artifacts-3.0.6.24.dist-info/METADATA
ibm_metrics_plugin_artifacts-3.0.6.24.dist-info/WHEEL
ibm_metrics_plugin_artifacts-3.0.6.24.dist-info/top_level.txt
ibm_metrics_plugin_artifacts-3.0.6.24.dist-info/RECORD
