Metadata-Version: 2.4
Name: ibm-metrics-plugin-artifacts
Version: 3.0.6.24
Summary: IBM Watson OpenScale Artifacts library
Author: IBM
Author-email: neelgade@in.ibm.com
Requires-Python: >=3.10
Dynamic: author
Dynamic: author-email
Dynamic: description
Dynamic: description-content-type
Dynamic: requires-python
Dynamic: summary
